optionloop/__init__.py
optionloop/_version.py
optionloop/optionloop.py
optionloop/tests/__init__.py
optionloop/tests/test.py
optionloop-1.0.5.dist-info/DESCRIPTION.rst
optionloop-1.0.5.dist-info/METADATA
optionloop-1.0.5.dist-info/RECORD
optionloop-1.0.5.dist-info/WHEEL
optionloop-1.0.5.dist-info/metadata.json
optionloop-1.0.5.dist-info/top_level.txt
optionloop-1.0.5.dist-info/zip-safe
