Metadata-Version: 2.0
Name: optionloop
Version: 1.0.5
Summary: Allows collapsing of nested for loops via dictionary iteration
Home-page: https://github.com/arghdos/optionLoop
Author: arghdos
Author-email: arghdos@gmail.com
License: GPL
Platform: UNKNOWN
Classifier: Development Status :: 5 - Production/Stable
Classifier: Intended Audience :: Developers
Classifier: License :: OSI Approved :: GNU General Public License v3 (GPLv3)
Classifier: Natural Language :: English
Classifier: Programming Language :: Python :: 2
Classifier: Programming Language :: Python :: 2.7
Classifier: Programming Language :: Python :: 3
Classifier: Programming Language :: Python :: 3.5
Classifier: Programming Language :: Python :: 3.6
